ardupyrpc/__init__.py
ardupyrpc/ardupyrpc.py
ardupyrpc-0.1.0.dist-info/licenses/LICENSE
examples/example.py
ardupyrpc-0.1.0.dist-info/METADATA
ardupyrpc-0.1.0.dist-info/WHEEL
ardupyrpc-0.1.0.dist-info/top_level.txt
ardupyrpc-0.1.0.dist-info/RECORD
