Metadata-Version: 2.4
Name: ardupyrpc
Version: 0.1.0
Summary: Python client for an Arduino RPC bridge using MsgPack over serial.
Author: Luca Macavero
License-Expression: MIT
Project-URL: Homepage, https://github.com/lu-maca/pyrpc
Keywords: arduino,teensyduino,rpc,serial,msgpack
Classifier: Programming Language :: Python :: 3
Classifier: Operating System :: OS Independent
Requires-Python: >=3.8
License-File: LICENSE
Requires-Dist: pyserial
Requires-Dist: msgpack
Dynamic: license-file
